<?xml version="1.0" standalone="yes"?>
<NewDataSet>
  <ADDLISTSVIEW>
    <ADDITIONAL_LIST_ID>LIST2</ADDITIONAL_LIST_ID>
    <ADDITIONAL_LIST_NAME>MODULLER</ADDITIONAL_LIST_NAME>
  </ADDLISTSVIEW>
  <ADDLISTSVIEW>
    <ADDITIONAL_LIST_ID>LIST3</ADDITIONAL_LIST_ID>
    <ADDITIONAL_LIST_NAME>TEZGAH</ADDITIONAL_LIST_NAME>
  </ADDLISTSVIEW>
  <ADDLISTSVIEW>
    <ADDITIONAL_LIST_ID>LIST4</ADDITIONAL_LIST_ID>
    <ADDITIONAL_LIST_NAME>KULP</ADDITIONAL_LIST_NAME>
  </ADDLISTSVIEW>
  <COLUMNMASKERVIEW>
    <COLUMN_MASKER_COLUMN_NAME>ITEM_ALTERNATIVE_CODE</COLUMN_MASKER_COLUMN_NAME>
    <COLUMN_MASKER_LISTS_LINK>True_False_False</COLUMN_MASKER_LISTS_LINK>
  </COLUMNMASKERVIEW>
  <COLUMNMASKERVIEW>
    <COLUMN_MASKER_COLUMN_NAME>ITEM_PRICE_TYPE</COLUMN_MASKER_COLUMN_NAME>
    <COLUMN_MASKER_LISTS_LINK>True_False_True</COLUMN_MASKER_LISTS_LINK>
  </COLUMNMASKERVIEW>
  <COLUMNMASKERVIEW>
    <COLUMN_MASKER_COLUMN_NAME>ITEM_PRICE</COLUMN_MASKER_COLUMN_NAME>
    <COLUMN_MASKER_LISTS_LINK>True_False_True</COLUMN_MASKER_LISTS_LINK>
  </COLUMNMASKERVIEW>
  <COLUMNMASKERVIEW>
    <COLUMN_MASKER_COLUMN_NAME>ITEM_NAME</COLUMN_MASKER_COLUMN_NAME>
    <COLUMN_MASKER_LISTS_LINK>True_False_False</COLUMN_MASKER_LISTS_LINK>
  </COLUMNMASKERVIEW>
  <COLUMNMASKERVIEW>
    <COLUMN_MASKER_COLUMN_NAME>ITEM_SUM</COLUMN_MASKER_COLUMN_NAME>
    <COLUMN_MASKER_LISTS_LINK>True_False_True</COLUMN_MASKER_LISTS_LINK>
  </COLUMNMASKERVIEW>
  <PIVOT_TABLES>
    <PIVOT_TABLE_NAME>Fiyatlandırma</PIVOT_TABLE_NAME>
    <PIVOT_SOURCE_TABLE>True_False</PIVOT_SOURCE_TABLE>
    <PIVOT_XCOL_SOURCE>ITEM_CODE</PIVOT_XCOL_SOURCE>
    <PIVOT_YCOL_SOURCE>MODUL</PIVOT_YCOL_SOURCE>
    <PIVOT_ZCOL_SOURCE>ITEM_QUANTITY</PIVOT_ZCOL_SOURCE>
    <PIVOT_AS_TREE>True</PIVOT_AS_TREE>
    <PIVOT_TOTAL_COL>False</PIVOT_TOTAL_COL>
    <PIVOT_TOTAL_ROW>False</PIVOT_TOTAL_ROW>
    <PIVOT_ALL_PRICES_ON_TREE>True</PIVOT_ALL_PRICES_ON_TREE>
    <PIVOT_HIDE_Z_COL_ON_TREE>False</PIVOT_HIDE_Z_COL_ON_TREE>
    <ONLY_LAST_PRICE_ONSTART>True</ONLY_LAST_PRICE_ONSTART>
    <PIVOT_USE_BILLTYPE>True</PIVOT_USE_BILLTYPE>
  </PIVOT_TABLES>
  <FIELDCOLLAPSEVIEW>
    <FIELD_COLLAPSED_LIST>False_True_False</FIELD_COLLAPSED_LIST>
    <SOURCE_SUM_FIELDS>ITEM_QUANTITY$QUANTITY$ITEM_SUM</SOURCE_SUM_FIELDS>
    <SOURCE_IGNORE_FIELDS>ITEM_PRICE_TYPE$ITEM_PRICE$ITEM_NAME</SOURCE_IGNORE_FIELDS>
  </FIELDCOLLAPSEVIEW>
  <FIELDCOLLAPSEVIEW>
    <FIELD_COLLAPSED_LIST>False_False_True</FIELD_COLLAPSED_LIST>
    <SOURCE_SUM_FIELDS>ITEM_QUANTITY$ITEM_SUM</SOURCE_SUM_FIELDS>
    <SOURCE_IGNORE_FIELDS>ITEM_PRICE_TYPE$ITEM_PRICE</SOURCE_IGNORE_FIELDS>
  </FIELDCOLLAPSEVIEW>
  <GENERALADVANCEDSETS>
    <SIZESEPERATE_ENABLE>False</SIZESEPERATE_ENABLE>
    <SIZESEPERATE_SIZEUNIT>size</SIZESEPERATE_SIZEUNIT>
    <ITEMREDIRECTION_ENABLE>False</ITEMREDIRECTION_ENABLE>
    <ITEMREDIRECTION_KEEPSOURCE>False</ITEMREDIRECTION_KEEPSOURCE>
    <ITEMCOLLAPSE_ENABLE>False</ITEMCOLLAPSE_ENABLE>
    <GROUPCLONE_COUNT>0</GROUPCLONE_COUNT>
    <ITEMEXPLOSION_ENABLE>False</ITEMEXPLOSION_ENABLE>
    <ITEMEXPLOSION_LEVEL>3</ITEMEXPLOSION_LEVEL>
    <COLUMN_MASKERVIEW_ENABLE>True</COLUMN_MASKERVIEW_ENABLE>
    <PIVOT_TABLES_ENABLE>True</PIVOT_TABLES_ENABLE>
    <OPTIPLAN_GROOVE_TO_EDGE_ENABLE>True</OPTIPLAN_GROOVE_TO_EDGE_ENABLE>
    <MAINPAGEMISSIONS>silent}Export To Template___silent}Exit</MAINPAGEMISSIONS>
    <XMLOUTPUTEXTENTION>xml</XMLOUTPUTEXTENTION>
  </GENERALADVANCEDSETS>
  <GENERALADVANCEDSETS />
</NewDataSet>